prml_helper/__init__.py
prml_helper/processor.py
prml_helper/utils.py
prml_helper-0.0.13.dist-info/METADATA
prml_helper-0.0.13.dist-info/WHEEL
prml_helper-0.0.13.dist-info/top_level.txt
prml_helper-0.0.13.dist-info/RECORD
