Metadata-Version: 2.1
Name: prml-helper
Version: 0.0.13
Summary: Helper functions for prml
Home-page: UNKNOWN
Author: qwertykid
Author-email: qwertykid583@gmail.com
License: UNKNOWN
Platform: UNKNOWN
Classifier: Programming Language :: Python :: 3
Classifier: License :: OSI Approved :: MIT License
Classifier: Operating System :: OS Independent
Requires-Python: >=3.6
Requires-Dist: nltk
Requires-Dist: numpy
Requires-Dist: pandas
Requires-Dist: scikit-learn
